DataLabICB/__init__.py
DataLabICB/chemistry.py
DataLabICB/.ipynb_checkpoints/chemistry-checkpoint.py
DataLabICB/datasets/chemistry/adsorption_all.json.gz
DataLabICB/datasets/chemistry/.ipynb_checkpoints/isotherm_all-checkpoint.json
datalabicb-0.1.3.dist-info/METADATA
datalabicb-0.1.3.dist-info/WHEEL
datalabicb-0.1.3.dist-info/licenses/LICENSE
datalabicb-0.1.3.dist-info/licenses/LICENSE-DATA
datalabicb-0.1.3.dist-info/RECORD
