Metadata-Version: 2.4
Name: DataLabICB
Version: 0.1.3
Summary: Python tools for loading, manipulating, and analyzing datasets used in the ICB laboratory. This package provides compressed datasets (`.json.gz`), a simple interface to load them (`Datasets`) and utility functions (chemistry, physics, etc.).
Author-email: Sébastien Mertès <sebastien.mertes@cnrs.fr>
License: MIT
License-File: LICENSE
License-File: LICENSE-DATA
Keywords: DATA,ICB,laboratory
Classifier: Intended Audience :: Science/Research
Classifier: License :: OSI Approved :: MIT License
Classifier: License :: Other/Proprietary License
Classifier: Operating System :: OS Independent
Classifier: Programming Language :: Python :: 3
Classifier: Topic :: Scientific/Engineering
Requires-Python: >=3.8
Requires-Dist: pandas>=1.4.0
